LICENSE.txt
MANIFEST.in
README.md
pyproject.toml
requirements.txt
setup.py
MedImageInsights/__init__.py
MedImageInsights.egg-info/PKG-INFO
MedImageInsights.egg-info/SOURCES.txt
MedImageInsights.egg-info/dependency_links.txt
MedImageInsights.egg-info/requires.txt
MedImageInsights.egg-info/top_level.txt
MedImageInsights/Distributed/Utils.py
MedImageInsights/Distributed/__init__.py
MedImageInsights/ImageDataLoader/__init__.py
MedImageInsights/ImageDataLoader/blob_storage.py
MedImageInsights/ImageDataLoader/build.py
MedImageInsights/ImageDataLoader/constants.py
MedImageInsights/ImageDataLoader/tsv.py
MedImageInsights/ImageDataLoader/tsv_file.py
MedImageInsights/ImageDataLoader/zipdata.py
MedImageInsights/ImageDataLoader/languages/__init__.py
MedImageInsights/ImageDataLoader/languages/prompt_engineering.py
MedImageInsights/ImageDataLoader/transforms/__init__.py
MedImageInsights/ImageDataLoader/transforms/autoaugment.py
MedImageInsights/ImageDataLoader/transforms/build.py
MedImageInsights/ImageDataLoader/transforms/threeaugment.py
MedImageInsights/ImageEncoder/__init__.py
MedImageInsights/ImageEncoder/build.py
MedImageInsights/ImageEncoder/coswin.py
MedImageInsights/ImageEncoder/davit_v1.py
MedImageInsights/ImageEncoder/registry.py
MedImageInsights/LangEncoder/__init__.py
MedImageInsights/LangEncoder/build.py
MedImageInsights/LangEncoder/registry.py
MedImageInsights/LangEncoder/transformer.py
MedImageInsights/Models/UniCLModel.py
MedImageInsights/Models/__init__.py
MedImageInsights/Models/medimageinsightmodel.py
MedImageInsights/Utils/Arguments.py
MedImageInsights/Utils/GeneraUtils.py
MedImageInsights/Utils/GlobalExceptHook.py
MedImageInsights/Utils/MPIAdapter.py
MedImageInsights/Utils/Utils.py
MedImageInsights/Utils/__init__.py
MedImageInsights/v20240927/config.yaml
MedImageInsights/v20240927/language_model/clip_tokenizer_v4162/merges.txt
MedImageInsights/v20240927/language_model/clip_tokenizer_v4162/special_tokens_map.json
MedImageInsights/v20240927/language_model/clip_tokenizer_v4162/tokenizer_config.json
MedImageInsights/v20240927/language_model/clip_tokenizer_v4162/vocab.json